o25/O25_hyp.py
o25/__init__.py
o25/test_O25.py
o25/Aux_functions/__init__.py
o25/Aux_functions/get_G_O25_4D.py
o25/Aux_functions/get_aw_bbw.py
o25-0.1.9.dist-info/licenses/LICENSE
o25-0.1.9.dist-info/METADATA
o25-0.1.9.dist-info/WHEEL
o25-0.1.9.dist-info/top_level.txt
o25-0.1.9.dist-info/RECORD
