Metadata-Version: 2.4
Name: o25
Version: 0.1.9
Summary: O25 algorithm for bidirectional correction of ocean color data and IOP retrieval
Home-page: https://github.com/jaipipor/O25
Author: Jaime Pitarch
Author-email: Jaime Pitarch <your-email@example.com>
License:                     GNU GENERAL PUBLIC LICENSE
Project-URL: Homepage, https://github.com/jaipipor/O25
Project-URL: Repository, https://github.com/jaipipor/O25
Requires-Python: >=3.7
License-File: LICENSE
Requires-Dist: numpy
Requires-Dist: scipy
Dynamic: author
Dynamic: home-page
Dynamic: license-file
Dynamic: requires-python
